chromatron/__init__.py
chromatron/array.fx
chromatron/astpp.py
chromatron/automaton.py
chromatron/chromatron.py
chromatron/chromatron_legacy.py
chromatron/code_gen.py
chromatron/explore_ast.py
chromatron/filewatcher.py
chromatron/graphics.py
chromatron/noise_test.fx
chromatron/pix.fx
chromatron/pix_count_test.fx
chromatron/pix_test_blue.fx
chromatron/pix_test_green.fx
chromatron/pix_test_red.fx
chromatron/rainbow.fx
chromatron/regs.fx
chromatron/run_vm.py
chromatron/startup.fx
chromatron/streamer.py
chromatron/test.fx
chromatron/test_code_gen.py
chromatron/test_if.fx
chromatron/test_kv.fx
chromatron/test_not.fx
chromatron/trig.py
chromatron/midi/__init__.py
chromatron/midi/apc40.py
chromatron/midi/midi.py
chromatron/midi/midi_config.py
chromatron/osc/OSC.py
chromatron/osc/osc_interface.py
chromatron-1.0.2.dist-info/DESCRIPTION.rst
chromatron-1.0.2.dist-info/METADATA
chromatron-1.0.2.dist-info/RECORD
chromatron-1.0.2.dist-info/WHEEL
chromatron-1.0.2.dist-info/entry_points.txt
chromatron-1.0.2.dist-info/metadata.json
chromatron-1.0.2.dist-info/top_level.txt
