Metadata-Version: 2.0
Name: chromatron
Version: 1.0.2
Summary: UNKNOWN
Home-page: UNKNOWN
Author: UNKNOWN
Author-email: UNKNOWN
License: GNU General Public License v3
Platform: UNKNOWN
Requires-Dist: catbus (>=1.0.2)
Requires-Dist: click (>=6.6)
Requires-Dist: crcmod (==1.7)
Requires-Dist: elysianfields (>=1.0)
Requires-Dist: sapphire (>=1.0.2)
